{
  "ghsa": {
    "consecutiveFailures": 0,
    "state": "closed",
    "lastSuccess": "2026-05-24T09:02:53.624Z",
    "lastFetchedAt": "2026-05-24T09:02:53.624Z"
  },
  "osv": {
    "consecutiveFailures": 0,
    "state": "closed",
    "lastSuccess": "2026-05-24T09:02:53.624Z",
    "lastFetchedAt": "2026-05-24T09:02:53.624Z"
  },
  "nvd": {
    "consecutiveFailures": 0,
    "state": "closed",
    "lastSuccess": "2026-05-24T09:02:53.624Z",
    "lastFetchedAt": "2026-05-24T09:02:53.624Z"
  },
  "packagist": {
    "consecutiveFailures": 0,
    "state": "closed",
    "lastSuccess": "2026-05-24T09:02:53.624Z",
    "lastFetchedAt": "2026-05-24T09:02:53.624Z"
  },
  "nextjs-releases": {
    "consecutiveFailures": 0,
    "state": "closed",
    "lastSuccess": "2026-05-24T09:02:53.624Z",
    "lastFetchedAt": "2026-05-24T09:02:53.624Z"
  },
  "arxiv-cs-cr": {
    "consecutiveFailures": 0,
    "state": "closed",
    "lastSuccess": "2026-05-24T05:29:45.560Z",
    "lastFetchedAt": "2026-05-24T05:29:45.560Z"
  },
  "nodejs-security": {
    "consecutiveFailures": 0,
    "state": "closed",
    "lastSuccess": "2026-05-24T09:02:53.624Z",
    "lastFetchedAt": "2026-05-24T09:02:53.624Z"
  },
  "php-security": {
    "consecutiveFailures": 0,
    "state": "closed",
    "lastSuccess": "2026-05-24T09:02:53.624Z",
    "lastFetchedAt": "2026-05-24T09:02:53.624Z"
  },
  "github-security-lab": {
    "consecutiveFailures": 0,
    "state": "closed",
    "lastSuccess": "2026-05-24T09:02:53.624Z",
    "lastFetchedAt": "2026-05-24T09:02:53.624Z"
  },
  "project-zero": {
    "consecutiveFailures": 0,
    "state": "closed",
    "lastSuccess": "2026-05-24T09:02:53.624Z",
    "lastFetchedAt": "2026-05-24T09:02:53.624Z"
  },
  "cisa-alerts": {
    "consecutiveFailures": 0,
    "state": "closed",
    "lastSuccess": "2026-05-24T09:02:53.624Z",
    "lastFetchedAt": "2026-05-24T09:02:53.624Z"
  },
  "cloudflare-blog": {
    "consecutiveFailures": 0,
    "state": "closed",
    "lastSuccess": "2026-05-24T09:02:53.624Z",
    "lastFetchedAt": "2026-05-24T09:02:53.624Z"
  },
  "vercel-changelog": {
    "consecutiveFailures": 0,
    "state": "closed",
    "lastSuccess": "2026-05-24T09:02:53.624Z",
    "lastFetchedAt": "2026-05-24T09:02:53.624Z"
  },
  "cve-org": {
    "consecutiveFailures": 0,
    "state": "closed",
    "lastSuccess": "2026-05-24T09:02:53.624Z",
    "lastFetchedAt": "2026-05-24T09:02:53.624Z"
  },
  "friendsofphp-advisories": {
    "consecutiveFailures": 0,
    "state": "closed",
    "lastSuccess": "2026-05-24T09:02:53.624Z",
    "lastFetchedAt": "2026-05-24T09:02:53.624Z"
  },
  "symfony-security": {
    "consecutiveFailures": 0,
    "state": "closed",
    "lastSuccess": "2026-05-24T09:02:53.624Z",
    "lastFetchedAt": "2026-05-24T09:02:53.624Z"
  },
  "github-repo-advisories": {
    "consecutiveFailures": 0,
    "state": "closed",
    "lastSuccess": "2026-05-24T09:02:53.624Z",
    "lastFetchedAt": "2026-05-24T09:02:53.624Z"
  },
  "cisa-vulnrichment": {
    "consecutiveFailures": 0,
    "state": "closed",
    "lastSuccess": "2026-05-24T03:21:23.336Z",
    "lastFetchedAt": "2026-05-24T03:21:23.336Z"
  },
  "ghsa-stack": {
    "consecutiveFailures": 0,
    "state": "closed",
    "lastSuccess": "2026-05-24T05:29:45.560Z",
    "lastFetchedAt": "2026-05-24T05:29:45.560Z"
  }
}
